MANIFEST.in
README.md
requirements.txt
setup.py
lip_generation/__init__.py
lip_generation/face_det.py
lip_generation/video_gen.py
lip_generation.egg-info/PKG-INFO
lip_generation.egg-info/SOURCES.txt
lip_generation.egg-info/dependency_links.txt
lip_generation.egg-info/requires.txt
lip_generation.egg-info/top_level.txt
lip_generation/face_detection/__init__.py
lip_generation/face_detection/face_alignment.py
lip_generation/face_detection/models.py
lip_generation/face_detection/utils.py
lip_generation/face_detection/detection/__init__.py
lip_generation/face_detection/detection/core.py
lip_generation/face_detection/detection/sfd/__init__.py
lip_generation/face_detection/detection/sfd/bbox.py
lip_generation/face_detection/detection/sfd/detect.py
lip_generation/face_detection/detection/sfd/net_s3fd.py
lip_generation/face_detection/detection/sfd/sfd_detector.py
lip_generation/video_generation/__init__.py
lip_generation/video_generation/conv.py
lip_generation/video_generation/wav2lip.py
lip_generation/video_generation/audio_mod/__init__.py
lip_generation/video_generation/audio_mod/audio.py
lip_generation/video_generation/audio_mod/hparams.py