Metadata-Version: 2.2
Name: lip-generation
Version: 0.5.0
Requires-Dist: pytest
Requires-Dist: setuptools
Requires-Dist: numpy
Requires-Dist: opencv-python
Requires-Dist: tqdm
Requires-Dist: torch
Requires-Dist: scipy
Requires-Dist: librosa
Dynamic: description
Dynamic: description-content-type
Dynamic: requires-dist
